frogbase/__init__.py
frogbase/__main__.py
frogbase/captions.py
frogbase/config.py
frogbase/core.py
frogbase/media.py
frogbase/models.py
frogbase-2.0.0a4.dist-info/LICENSE
frogbase-2.0.0a4.dist-info/METADATA
frogbase-2.0.0a4.dist-info/WHEEL
frogbase-2.0.0a4.dist-info/entry_points.txt
frogbase-2.0.0a4.dist-info/RECORD
