Metadata-Version: 2.1
Name: frogbase
Version: 2.0.0a4
Summary: FrogBase simplifies the download-transcribe-embed-index workflow for multi-media content. It does so by linking content from various platforms with speech-to-text models, image & text encoders and embedding stores.
Home-page: https://hayabhay.github.io/frogbase
License: MIT
Author: Abhay Kashyap
Requires-Python: >=3.8, !=2.7.*, !=3.0.*, !=3.1.*, !=3.2.*, !=3.3.*, !=3.4.*, !=3.5.*, !=3.6.*, !=3.7.*
Classifier: Development Status :: 3 - Alpha
Classifier: Intended Audience :: Developers
Classifier: License :: OSI Approved :: MIT License
Classifier: Natural Language :: English
Classifier: Programming Language :: Python :: 3
Classifier: Programming Language :: Python :: 3.9
Classifier: Programming Language :: Python :: 3.10
Classifier: Programming Language :: Python :: 3.11
Classifier: Programming Language :: Python :: 3.8
Classifier: Topic :: Software Development :: Libraries :: Python Modules
Requires-Dist: hnswlib (>=0.7.0,<0.8.0)
Requires-Dist: humanize (>=4.6.0,<5.0.0)
Requires-Dist: loguru (>=0.7.0,<0.8.0)
Requires-Dist: openai-whisper (>=20230314,<20230315)
Requires-Dist: pydantic (>=2.0,<3.0)
Requires-Dist: sentence-transformers (>=2.2.2,<3.0.0)
Requires-Dist: tinydb (>=4.8.0,<5.0.0)
Requires-Dist: torch (>=2.0.0,!=2.0.1)
Requires-Dist: webvtt-py (>=0.4.6,<0.5.0)
Requires-Dist: yt-dlp (>=2023.3.4,<2024.0.0)
Project-URL: Changelog, https://github.com/hayabhay/frogbase/releases
Project-URL: Documentation, https://hayabhay.github.io/frogbase
Project-URL: Repository, https://github.com/hayabhay/frogbase
